scratchapi.py
scratchapi-1.4.1.dist-info/DESCRIPTION.rst
scratchapi-1.4.1.dist-info/METADATA
scratchapi-1.4.1.dist-info/RECORD
scratchapi-1.4.1.dist-info/WHEEL
scratchapi-1.4.1.dist-info/metadata.json
scratchapi-1.4.1.dist-info/top_level.txt
