Metadata-Version: 2.0
Name: scratchapi
Version: 1.4.1
Summary: ScratchAPI is a Scratch API interface written in Python
Home-page: https://github.com/Dylan5797/ScratchAPI
Author: Dylan Beswick
Author-email: djbeswick64@gmail.com
License: UNKNOWN
Keywords: scratch,api,cloud
Platform: UNKNOWN
Classifier: Development Status :: 3 - Alpha
Classifier: Intended Audience :: Developers
Classifier: Programming Language :: Python :: 3
Requires-Dist: requests
